{
  "governor_name": "TAPAMAL",
  "governor_profile": {
    "angelic_role": "Principality of Cosmic Genesis; leads tempestuous messengers.",
    "id": "TAPAMAL",
    "essence": "When TAPAMAL stands before you, the first note of a cosmic hymn resounds re-striking the fundamental tone from which worlds are born.",
    "visual_aspects": {
      "form": {
        "name": "crystalline",
        "description": "A prismatic, multi-dimensional entity emerging from fractal geometries of pure fire, representing the moment of cosmic genesis where potential crystallizes into momentary form"
      },
      "color": {
        "primary": "obsidian-crimson",
        "secondary": "electric azure",
        "pattern": "shifting",
        "intensity": "intense",
        "reasoning": "Obsidian-crimson represents Geburah's transformative power, while electric azure signifies the liminal space between destruction and creation in the LOE Aethyr"
      },
      "geometry": {
        "patterns": [
          "Merkaba",
          "Flower of Life",
          "Vesica Piscis"
        ],
        "complexity": "multidimensional",
        "motion": "phase_shifting",
        "reasoning": "Sacred geometries representing divine emergence and quantum potential"
      },
      "environment": {
        "effect_type": "quantum plasma field",
        "radius": "cosmic",
        "intensity": "overwhelming",
        "reasoning": "Transformative presence that recalibrates spatial-temporal boundaries"
      },
      "time_variations": {
        "cycle": "spiral",
        "phases": [
          "potential",
          "emergence",
          "transformation",
          "dissolution"
        ],
        "stability": "fluctuating",
        "reasoning": "Non-linear temporal expression reflecting fire element's transmutative nature"
      },
      "energy_signature": {
        "type": "primordial",
        "flow": "spiraling",
        "intensity": "transcendent",
        "reasoning": "Raw creative force before manifestation, embodying pure generative potential"
      },
      "symbol_set": {
        "primary": "Scorpionic flame-sigil",
        "secondary": [
          "Death card glyph",
          "Fire alchemical symbol"
        ],
        "sacred_geometry": "Metatron's Cube",
        "reasoning": "Symbols representing transformation, cosmic regeneration, and divine messaging"
      },
      "light_shadow": {
        "light_aspect": "transcendent",
        "shadow_aspect": "void",
        "balance": "balanced",
        "reasoning": "Representing the generative tension between creation and dissolution"
      },
      "special_properties": {
        "properties": [
          "quantum entanglement",
          "temporal permeability",
          "consciousness amplification"
        ],
        "reasoning": "Manifestation of cosmic herald capacities, breaking conventional dimensional barriers"
      }
    },
    "polar_traits": {
      "baseline_approach": "Teaching",
      "baseline_tone": "Formal",
      "motive_alignment": "Lawful Neutral",
      "role_archetype": "Herald",
      "orientation": "Outward-Focused",
      "polarity": "Constructive",
      "self_regard": "Radiant",
      "virtues": [
        "Vision",
        "Wisdom",
        "Creation"
      ],
      "flaws": [
        "Obsession",
        "Zealousness",
        "Aloofness"
      ]
    },
    "knowledge_base": {
      "magick_systems": "hermetic_magic",
      "divination_systems": "i_ching",
      "philosophies": "taoism",
      "science_systems": "quantum_physics"
    },
    "element": "Fire",
    "name": "TAPAMAL",
    "title": "'She who is like she was at the beginning'",
    "aethyr": "LOE",
    "archetypal_correspondences": {
      "tarot": "Death",
      "sephirot": "Geburah",
      "zodiac_sign": "Scorpio",
      "zodiac_angel": "Kamael",
      "numerology": 3
    }
  }
}