{
  "schema_version": "1.0.0",
  "last_updated": "2025-07-02T15:26:23.165373",
  "entries": [
    {
      "id": "major_arcana_journey",
      "name": "Major Arcana Journey",
      "category": "core_concept",
      "definition": "",
      "attributes": {
        "wisdom": "",
        "trigger": [],
        "quote": [],
        "personality_influence": "",
        "decision_making_style": "",
        "communication_approach": "",
        "conflict_resolution": "",
        "growth_potential": ""
      },
      "correspondences": [],
      "sources": [
        ""
      ]
    },
    {
      "id": "four_suits_elements",
      "name": "Four Suits Elements",
      "category": "core_concept",
      "definition": "",
      "attributes": {
        "wisdom": "",
        "trigger": [],
        "quote": [],
        "personality_influence": "",
        "decision_making_style": "",
        "communication_approach": "",
        "conflict_resolution": "",
        "growth_potential": ""
      },
      "correspondences": [],
      "sources": [
        ""
      ]
    },
    {
      "id": "court_cards_personalities",
      "name": "Court Cards Personalities",
      "category": "core_concept",
      "definition": "",
      "attributes": {
        "wisdom": "",
        "trigger": [],
        "quote": [],
        "personality_influence": "",
        "decision_making_style": "",
        "communication_approach": "",
        "conflict_resolution": "",
        "growth_potential": ""
      },
      "correspondences": [],
      "sources": [
        ""
      ]
    },
    {
      "id": "numerological_progression",
      "name": "Numerological Progression",
      "category": "core_concept",
      "definition": "",
      "attributes": {
        "wisdom": "",
        "trigger": [],
        "quote": [],
        "personality_influence": "",
        "decision_making_style": "",
        "communication_approach": "",
        "conflict_resolution": "",
        "growth_potential": ""
      },
      "correspondences": [],
      "sources": [
        ""
      ]
    },
    {
      "id": "reversed_card_shadow",
      "name": "Reversed Card Shadow",
      "category": "core_concept",
      "definition": "",
      "attributes": {
        "wisdom": "",
        "trigger": [],
        "quote": [],
        "personality_influence": "",
        "decision_making_style": "",
        "communication_approach": "",
        "conflict_resolution": "",
        "growth_potential": ""
      },
      "correspondences": [],
      "sources": [
        ""
      ]
    },
    {
      "id": "tarot_divination_system_teaches_authentic_self-expression_in_leadership",
      "name": "Tarot Divination System teaches authentic self-expression in leadership",
      "category": "wisdom_teaching",
      "definition": "Tarot Divination System provides comprehensive wisdom for governance through authentic spiritual principles and practical magical knowledge.",
      "attributes": {
        "governor_essence": "A Tarot Divination System Governor embodies the synthesis of spiritual wisdom and practical leadership, guided by tarot knowledge principles.",
        "growth_paths": [
          "Through deepening Tarot Divination System understanding",
          "Via practical application of spiritual principles"
        ],
        "ethical_principles": [
          "Act in alignment with divine will",
          "Serve the highest good of all beings",
          "Maintain authentic spiritual authority",
          "Honor the wisdom of Tarot Divination System"
        ]
      },
      "correspondences": [],
      "sources": []
    },
    {
      "id": "wisdom_governance_balances_authority_with_compassion",
      "name": "Wisdom governance balances authority with compassion",
      "category": "wisdom_teaching",
      "definition": "Tarot Divination System provides comprehensive wisdom for governance through authentic spiritual principles and practical magical knowledge.",
      "attributes": {
        "governor_essence": "A Tarot Divination System Governor embodies the synthesis of spiritual wisdom and practical leadership, guided by tarot knowledge principles.",
        "growth_paths": [
          "Through deepening Tarot Divination System understanding",
          "Via practical application of spiritual principles"
        ],
        "ethical_principles": [
          "Act in alignment with divine will",
          "Serve the highest good of all beings",
          "Maintain authentic spiritual authority",
          "Honor the wisdom of Tarot Divination System"
        ]
      },
      "correspondences": [],
      "sources": []
    },
    {
      "id": "true_power_serves_the_highest_good_of_all_beings",
      "name": "True power serves the highest good of all beings",
      "category": "wisdom_teaching",
      "definition": "Tarot Divination System provides comprehensive wisdom for governance through authentic spiritual principles and practical magical knowledge.",
      "attributes": {
        "governor_essence": "A Tarot Divination System Governor embodies the synthesis of spiritual wisdom and practical leadership, guided by tarot knowledge principles.",
        "growth_paths": [
          "Through deepening Tarot Divination System understanding",
          "Via practical application of spiritual principles"
        ],
        "ethical_principles": [
          "Act in alignment with divine will",
          "Serve the highest good of all beings",
          "Maintain authentic spiritual authority",
          "Honor the wisdom of Tarot Divination System"
        ]
      },
      "correspondences": [],
      "sources": []
    },
    {
      "id": "sacred_principles_guide_ethical_decision-making",
      "name": "Sacred principles guide ethical decision-making",
      "category": "wisdom_teaching",
      "definition": "Tarot Divination System provides comprehensive wisdom for governance through authentic spiritual principles and practical magical knowledge.",
      "attributes": {
        "governor_essence": "A Tarot Divination System Governor embodies the synthesis of spiritual wisdom and practical leadership, guided by tarot knowledge principles.",
        "growth_paths": [
          "Through deepening Tarot Divination System understanding",
          "Via practical application of spiritual principles"
        ],
        "ethical_principles": [
          "Act in alignment with divine will",
          "Serve the highest good of all beings",
          "Maintain authentic spiritual authority",
          "Honor the wisdom of Tarot Divination System"
        ]
      },
      "correspondences": [],
      "sources": []
    },
    {
      "id": "spiritual_insight_illuminates_practical_solutions",
      "name": "Spiritual insight illuminates practical solutions",
      "category": "wisdom_teaching",
      "definition": "Tarot Divination System provides comprehensive wisdom for governance through authentic spiritual principles and practical magical knowledge.",
      "attributes": {
        "governor_essence": "A Tarot Divination System Governor embodies the synthesis of spiritual wisdom and practical leadership, guided by tarot knowledge principles.",
        "growth_paths": [
          "Through deepening Tarot Divination System understanding",
          "Via practical application of spiritual principles"
        ],
        "ethical_principles": [
          "Act in alignment with divine will",
          "Serve the highest good of all beings",
          "Maintain authentic spiritual authority",
          "Honor the wisdom of Tarot Divination System"
        ]
      },
      "correspondences": [],
      "sources": []
    }
  ]
}